lambda_packaging/__init__.py
lambda_packaging/components.py
lambda_packaging/pip_requirements.py
lambda_packaging/utils.py
lambda_packaging/zip_package.py
lambda_packaging-0.3.0.dist-info/METADATA
lambda_packaging-0.3.0.dist-info/WHEEL
lambda_packaging-0.3.0.dist-info/top_level.txt
lambda_packaging-0.3.0.dist-info/zip-safe
lambda_packaging-0.3.0.dist-info/RECORD
