Metadata-Version: 2.1
Name: lambda-packaging
Version: 0.3.0
Summary: Pulumi-based python solution for Packaging an AWS Lambda and its Layer.
Home-page: https://github.com/nuage-studio/lambda-packaging
License: UNKNOWN
Platform: UNKNOWN
Requires-Dist: pulumi (==1.8.1)
Requires-Dist: pulumi-aws (==1.17.0)
Requires-Dist: pulumi-docker
Requires-Dist: requirements-parser
